.coveragerc
.gitignore
MANIFEST.in
README.rst
bootstrap.py
setup.py
test-plone-4.1.x.cfg
test-plone-4.2.x.cfg
test-plone-4.3.x.cfg
test-plone-base.cfg
docs/HISTORY.txt
docs/LICENSE.GPL
docs/LICENSE.txt
docs/plonetheme-drupal-screenshot.png
src/plonetheme/__init__.py
src/plonetheme.drupal.egg-info/PKG-INFO
src/plonetheme.drupal.egg-info/SOURCES.txt
src/plonetheme.drupal.egg-info/dependency_links.txt
src/plonetheme.drupal.egg-info/entry_points.txt
src/plonetheme.drupal.egg-info/namespace_packages.txt
src/plonetheme.drupal.egg-info/not-zip-safe
src/plonetheme.drupal.egg-info/requires.txt
src/plonetheme.drupal.egg-info/top_level.txt
src/plonetheme/drupal/__init__.py
src/plonetheme/drupal/configure.zcml
src/plonetheme/drupal/rebuild_i18n.sh
src/plonetheme/drupal/testing.py
src/plonetheme/drupal/Extensions/Install.py
src/plonetheme/drupal/Extensions/__init__.py
src/plonetheme/drupal/browser/__init__.py
src/plonetheme/drupal/browser/configure.zcml
src/plonetheme/drupal/browser/interfaces.py
src/plonetheme/drupal/browser/plone-versus-drupal.pt
src/plonetheme/drupal/jbot/plone.app.layout.viewlets.logo.pt
src/plonetheme/drupal/locales/plonetheme.drupal.pot
src/plonetheme/drupal/locales/en/LC_MESSAGES/plonetheme.drupal.po
src/plonetheme/drupal/locales/fr/LC_MESSAGES/plonetheme.drupal.po
src/plonetheme/drupal/profiles/default/browserlayer.xml
src/plonetheme/drupal/profiles/default/cssregistry.xml
src/plonetheme/drupal/profiles/default/jsregistry.xml
src/plonetheme/drupal/profiles/default/metadata.xml
src/plonetheme/drupal/profiles/default/skins.xml
src/plonetheme/drupal/profiles/default/theme.xml
src/plonetheme/drupal/profiles/uninstall/browserlayer.xml
src/plonetheme/drupal/profiles/uninstall/cssregistry.xml
src/plonetheme/drupal/profiles/uninstall/jsregistry.xml
src/plonetheme/drupal/profiles/uninstall/metadata.xml
src/plonetheme/drupal/profiles/uninstall/skins.xml
src/plonetheme/drupal/skins/plonetheme_drupal_custom/favicon.ico
src/plonetheme/drupal/skins/plonetheme_drupal_custom/logo.png
src/plonetheme/drupal/static/manifest.cfg
src/plonetheme/drupal/static/rules.xml
src/plonetheme/drupal/static/theme-one-column.html
src/plonetheme/drupal/static/theme-three-columns.html
src/plonetheme/drupal/static/theme-two-columns-left.html
src/plonetheme/drupal/static/theme-two-columns-right.html
src/plonetheme/drupal/static/css/ie-fixes.css
