Metadata-Version: 1.0
Name: plonetheme.drupal
Version: 1.1
Summary: Get all the power of Drupal for Plone ;)
Home-page: https://github.com/sylvainb/plonetheme.drupal
Author: Sylvain Boureliou
Author-email: sylvain.boureliou@gmail.com
License: GPL
Keywords: plone theme diazo web zope drupal
Platform: UNKNOWN
Classifier: Framework :: Plone
Classifier: Framework :: Plone :: 4.1
Classifier: Framework :: Plone :: 4.2
Classifier: Programming Language :: Python
Classifier: Topic :: Software Development :: Libraries :: Python Modules
